[{"doc": "工程师知识.txt", "chunk_idx": 0, "text": "**文档编号：** TECH-2026-001 **适用设备：** 六轴工业机器人（通用型） **编写人：** 首席机械工程师\n\n#### 1. 核心故障案例：E-102 伺服电机过热\n\n- **故障代码：** `ERR_MOTOR_OVERHEAT_102`\n- **现象：** 机器人 3 号轴（J3）在高速运行时突然停机，示教器显示电流异常波动，电机外壳温度超过 85°C。\n- **专家经验：** 此类故障 80% 的原因并非电机损坏，而是因为**抱闸系统未完全释放**或**减速机润滑脂劣化**导致的阻力增大。\n- **排查步骤：**\n  1. 检查 3 轴抱闸反馈信号，确认电磁阀动作是否迟缓。\n  2. 观察减速机渗油情况，若发现黑色粘稠物，需立即更换极压复合锂基润滑脂。\n  3. 临时对策：若生产任务紧急，可尝试在控制参数中将 `Acceleration_Ratio` 降低 15%。\n\n#### 2. 通用经验：传感器信号干扰（EMC）\n\n- **现象：** 诊断日志中出现大量随机的 I/O 信号抖动，无固定错误码。\n- **排查逻辑：** 检查电柜内部屏蔽层接地情况。通常是因"}, {"doc": "工程师知识.txt", "chunk_idx": 1, "text": "机的 I/O 信号抖动，无固定错误码。\n- **排查逻辑：** 检查电柜内部屏蔽层接地情况。通常是因为拖链内部动力线与信号线并行走线，导致电磁感应干扰。\n- **改进：** 在信号输入端增加 0.1uF 的滤波电容。"}]